setup.py
blockext_sphero/__init__.py
blockext_sphero/__main__.py
blockext_sphero.egg-info/PKG-INFO
blockext_sphero.egg-info/SOURCES.txt
blockext_sphero.egg-info/dependency_links.txt
blockext_sphero.egg-info/requires.txt
blockext_sphero.egg-info/top_level.txt