Metadata-Version: 1.1
Name: blockext-sphero
Version: 0.2.2
Summary: Orbotix Sphero extension for Scratch 2.0 and Snap!
Home-page: https://github.com/blockext/sphero
Author: Tim Radvan, Connor Hudson
Author-email: blob8108@gmail.com
License: MIT
Platform: UNKNOWN
Classifier: Programming Language :: Python
